tnsgrt/__init__.py
tnsgrt/michell.py
tnsgrt/optim.py
tnsgrt/prism.py
tnsgrt/stiffness.py
tnsgrt/structure.py
tnsgrt/utils.py
tnsgrt/plotter/__init__.py
tnsgrt/plotter/matplotlib.py
tnsgrt/plotter/plotter.py
tnsgrt/plotter/vispy.py
tnsgrt-0.6.dist-info/METADATA
tnsgrt-0.6.dist-info/WHEEL
tnsgrt-0.6.dist-info/licenses/LICENSE
tnsgrt-0.6.dist-info/RECORD
