Metadata-Version: 2.1
Name: tnsgrt
Version: 0.6
Summary: Python library with support for analysis and design of Tensegrity structures
Project-URL: Homepage, https://github.com/mcdeoliveira/tensegrity
Author-email: "Mauricio C. de Oliveira" <mcdeoliveira@duck.com>
License: MIT License
License-File: LICENSE
Keywords: Tensegrity,structures,trusses
Classifier: Development Status :: 3 - Alpha
Classifier: Intended Audience :: Other Audience
Classifier: License :: OSI Approved :: MIT License
Classifier: Programming Language :: Python :: 3.7
Classifier: Topic :: Scientific/Engineering
Requires-Python: >3.7
Requires-Dist: cvxpy
Requires-Dist: matplotlib
Requires-Dist: more-itertools
Requires-Dist: numpy
Requires-Dist: pandas
Requires-Dist: parameterized
Requires-Dist: scipy
Requires-Dist: typing-extensions
Requires-Dist: vispy
